{
  "tplId": "feralStalker",
  "name": "Feral Stalker",
  "type": "Creature",
  "sub": "Cat",
  "cost": {
    "G": 1,
    "C": 2
  },
  "power": 2,
  "toughness": 2,
  "art": "🐅",
  "text": "When this attacks, it gets +2/+2 EOT.",
  "triggers": [
    {
      "event": "attacks",
      "condId": "thisAttacks",
      "text": "When ~ attacks, it gets +2/+2 EOT.",
      "effects": [
        {
          "kind": "pump",
          "target": "self",
          "power": 2,
          "toughness": 2
        }
      ]
    }
  ],
  "color": "G",
  "colors": [
    "G"
  ]
}
